trasyn/__init__.py
trasyn/__main__.py
trasyn/_version.py
trasyn/gates.py
trasyn/mps.py
trasyn/synthesis copy.py
trasyn/synthesis.py
trasyn/unique_matrices.py
trasyn/utils.py
trasyn/assets/tsh/duplicates_13.json
trasyn/assets/tsh/sequences_13.json
trasyn/assets/tsh/tensor_13.npy
trasyn/assets/tshxyz/duplicates_13.json
trasyn/assets/tshxyz/sequences_13.json
trasyn/assets/tshxyz/tensor_13.npy
trasyn-0.2.0.dist-info/licenses/LICENSE
trasyn-0.2.0.dist-info/METADATA
trasyn-0.2.0.dist-info/WHEEL
trasyn-0.2.0.dist-info/entry_points.txt
trasyn-0.2.0.dist-info/top_level.txt
trasyn-0.2.0.dist-info/RECORD
