Metadata-Version: 2.4
Name: trasyn
Version: 0.2.0
Summary: trasyn: a unitary synthesis method for fault-tolerant quantum computing
Author-email: Tianyi Hao <tianyi.hao@wisc.edu>
License-Expression: MIT
Project-URL: Repository, https://github.com/haoty/trasyn
Keywords: quantum computing
Classifier: Programming Language :: Python :: 3
Classifier: Topic :: Scientific/Engineering :: Quantum Computing
Classifier: Intended Audience :: Science/Research
Classifier: Intended Audience :: Developers
Requires-Python: >=3.10
License-File: LICENSE
Requires-Dist: numpy>=1.26.4
Requires-Dist: psutil>=6
Provides-Extra: cupy-cuda11
Requires-Dist: cupy-cuda11x>=13.3.0; extra == "cupy-cuda11"
Provides-Extra: cupy-cuda12
Requires-Dist: cupy-cuda12x>=13.3.0; extra == "cupy-cuda12"
Provides-Extra: qiskit
Requires-Dist: qiskit>=1.2.4; extra == "qiskit"
Dynamic: license-file
